{
    "date": "Friday, June 17, 2022",
    "scores": [
        {
            "rank": "1",
            "name": "PT ",
            "time": "0:34"
        },
        {
            "rank": "2",
            "name": "Megan ",
            "time": "0:41"
        },
        {
            "rank": "3",
            "name": "mcnugget ",
            "time": "1:15"
        },
        {
            "rank": "4",
            "name": "tonedew ",
            "time": "1:20"
        },
        {
            "rank": "5",
            "name": "Maithy ",
            "time": "2:10"
        },
        {
            "rank": "6",
            "name": "Kha ",
            "time": "3:31"
        }
    ]
}