{
    "date": "Saturday, September 17, 2022",
    "scores": [
        {
            "rank": "1",
            "name": "mcnugget ",
            "time": "1:33"
        },
        {
            "rank": "2",
            "name": "PT ",
            "time": "3:44"
        },
        {
            "rank": "3",
            "name": "Jacqui ",
            "time": "4:10"
        },
        {
            "rank": "4",
            "name": "Maithy ",
            "time": "4:39"
        },
        {
            "rank": "5",
            "name": "Kha ",
            "time": "7:01"
        },
        {
            "rank": "6",
            "name": "tonedew ",
            "time": "7:49"
        },
        {
            "rank": "7",
            "name": "Mikaela ",
            "time": "8:17"
        }
    ]
}